<?xml version="1.0" encoding="ISO-8859-1"?><?xml-model href="../../../schemata/shelley-godwin-page.rnc"
  type="application/relax-ng-compact-syntax"?><?xml-stylesheet type="text/xsl"
  href="../../../xsl/page-proof.xsl"?>
<surface xmlns="http://www.tei-c.org/ns/1.0" xmlns:sga="http://shelleygodwinarchive.org/ns/1.0"
  ulx="0" uly="0" lrx="4966" lry="7248"
  xml:id="ox-ms_shelley_adds_c4-0463" partOf="#ox-ms_shelley_adds_c4"
  sga:shelfmark="MS. Shelley adds. c. 4" sga:folio="303r">
  <graphic url="http://shelleygodwinarchive.org/images/ox/ox-ms_shelley_adds_c4-0463.jp2"/>
  <zone type="main">
    <line>The Author sends "Queen Mab" to</line>
    <line>Mr. Waller, as Cardinal Wolsey was sent</line>
    <line>to Heaven, "with all his imperfections</line>
    <line>on his head." It was composed</line>
    <line>in early youth, &amp; is full of those errors</line>
    <line>which belong to youth, as far as</line>
    <line>arrangement of imagery &amp; language</line>
    <line>&amp; a connected plan, is concerned.</line>
    <line>But it<del rend="strikethrough">s</del> <del rend="strikethrough">is</del> was a sincere overflo<del rend="strikethrough">wing</del></line>
    <line>-wing of the heart &amp; mind, &amp; that</line>
    <line>at a period when they are most</line>
    <line>uncorrupted &amp; pure. It is the Author's</line>
    <line>boast, <del rend="strikethrough">&amp;</del> that constitutes no small portion</line>
    <line>of his happiness that, after six</line>
    <line>years of added experience &amp; reflec<del rend="strikethrough">tion</del></line>
    <line>-tion, the doctrines of equality &amp;</line>
    <line>liberty &amp; disinteredness, &amp;</line>
  </zone>
</surface>
