<?xml version="1.0" encoding="ISO-8859-1"?><?xml-model href="../../../schemata/shelley-godwin-page.rnc"
  type="application/relax-ng-compact-syntax"?><?xml-stylesheet type="text/xsl"
  href="../../../xsl/page-proof.xsl"?>
<surface xmlns="http://www.tei-c.org/ns/1.0" xmlns:mith="http://mith.umd.edu/sc/ns1#"
  ulx="0" uly="0" lrx="4966" lry="7248"
  xml:id="ox-ms_shelley_adds_c4-0397" partOf="#ox-ms_shelley_adds_c4"
  mith:shelfmark="MS. Shelley adds. c. 4" mith:folio="269r">
  <graphic url="http://shelleygodwinarchive.org/images/ox/ox-ms_shelley_adds_c4-0397.jp2"/>
  <zone type="main">
    <line>Custom has been found to</line>
    <line><del rend="strikethrough">habit</del> <del rend="strikethrough">will</del> reconcile the animal system to habits the most unna<del rend="strikethrough">tural</del></line>
    <line>-tural &amp; pernicious. Narcotic poisons have been gradually</line>
    <line>ceased</line>
    <line>swallowed until they have <del rend="strikethrough">failed</del> to <del rend="strikethrough">produce</del> thier accustomed</line>
    <line>effect, although they have never failed eventually to</line>
    <line>produce disease &amp; death. <del rend="strikethrough">It is the</del> Every being with which</line>
    <line>we are acquainted invariably attempts to accommodate</line>
    <line>itself to the circumstances of its situation; <del rend="strikethrough">it does</del></line>
    <line>nevertheless</line>
    <line><del rend="strikethrough">not fail however to</del> <del rend="strikethrough"><unclear></unclear>it</del> it exhauts <del rend="strikethrough">however</del> in the</line>
    <line>effort much of its vital energy<del rend="strikethrough">,</del>. <del rend="strikethrough">and</del> <del rend="strikethrough">a</del> A <del rend="strikethrough">tree</del> <del rend="strikethrough">oak will</del></line>
    <line><del rend="strikethrough">grow upon the barren rocks, but it <del rend="strikethrough">will at</del> is capable of</del></line>
    <line><del rend="strikethrough">attaining to greater age &amp; perfection</del> a willow will attain</line>
    <line>its perfection</line>
    <line>to <del rend="strikethrough">greater perfection</del> by the bank of a river, because</line>
    <line>this situation is analogous to its nature; place it</line>
    <line>that soil which is congenial to the fir tree,: <del rend="strikethrough">&amp;</del> it will live</line>
    <line>indeed if it survive the shock of transplantation but will</line>
    <line>become a <del rend="strikethrough">stunted</del> diseased &amp; stunted shrub. <del rend="strikethrough">Lambs</del></line>
    <line>x</line>
    <line><del rend="strikethrough">have eaten flesh, until they have refused thier natural</del></line>
    <line>x</line>
    <line><del rend="strikethrough">diet</del>. Horses, sheep oxen &amp; even wood pi<del rend="strikethrough">d</del>geons have been</line>
    <line>taught to live upon flesh until they have loathed thier</line>
    <line>natural <del rend="strikethrough">diet x</del> aliment</line>
    <line><del rend="strikethrough">accustomed aliment</del>. No argument therefore can be</line>
    <line>adduced in favour of any system of diet from the</line>
    <line>mere fact of its being generally used, so long as disease</line>
    <line>among    unfailing</line>
    <line>&amp; meagreness &amp; misery are observed to <del rend="strikethrough">be its</del> concomitants</line>
    <line>xRi x: x: x:   &#8212;&#8212;-</line>
    <line>lies</line>
    <line><del rend="strikethrough">It</del> Here then <del rend="strikethrough">is</del> exposed one of the most important sources of the</line>
    <line>If these reasonig have any force</line>
    <line>wretchedness of man. <del rend="strikethrough">It is clear</del> <del rend="strikethrough">that</del> mankind is in the</line>
    <line><del rend="strikethrough">therefore</del></line>
    <line>daily practise of an unnatural habit, <del rend="strikethrough">&amp; that</del> the consequences</line>
    <line>of which</line>
    <line><del rend="strikethrough">of this habit</del> cannot fail to be eminently pernicious.</line>
    <line>It is a duty which every individual owes to <del rend="strikethrough">those</del> <del rend="strikethrough">w</del> himself</line>
    <line>to posterity</line>
    <line>to those who are influenced by his example, &amp; to those</line>
    <line>health &amp;    any portion of their</line>
    <line>who decend in any manner on his existence for <del rend="strikethrough">their support</del></line>
    <line><del rend="strikethrough">&amp; to posterity</del> resolutely</line>
    <line>happiness, to break ?this <del rend="strikethrough">?this</del> unnatural <del rend="strikethrough">&amp; destructive</del></line>
    <line>thus pregnant with inexhaustible &amp; measureless calamity</line>
    <line>practise <del rend="strikethrough">resolutely &amp; at once</del>. <del rend="strikethrough">It is</del> Those who are</line>
    <line><del rend="strikethrough">convinced by these rcasonings</del> persuaded of the point which</line>
    <line>it is the object of this enquiry to establish, are</line>
    <line>x Ritson</line>
  </zone>
</surface>
