<?xml version="1.0" encoding="UTF-8"?>
<?xml-model href="../../../schemata/shelley-godwin-page.rng" type="application/xml" schematypens="http://purl.oclc.org/dsdl/schematron"?>
<?xml-model href="../../../schemata/shelley-godwin-page.rng" type="application/xml" schematypens="http://relaxng.org/ns/structure/1.0"?>
<surface xmlns="http://www.tei-c.org/ns/1.0" xmlns:mith="http://mith.umd.edu/sc/ns1#"
  ulx="0" uly="0" lrx="4966" lry="7248"
  xml:id="ox-ms_shelley_adds_c4-0061" partOf="#ox-ms_shelley_adds_c4"
  mith:shelfmark="MS. Shelley adds. c. 4" mith:folio="26v">
  <graphic url="http://shelleygodwinarchive.org/images/ox/ox-ms_shelley_adds_c4-0061.jp2"/>
  <zone type="main">
    <line><del rend="strikethrough">lives</del></line>
    <line><del rend="strikethrough">Is <unclear>sna</unclear></del> <del rend="strikethrough">Their hearts in opposition</del></line>
    <line>Their natures, <del rend="strikethrough">in a leash while</del>  still may</line>
    <line>snaps . . . <del rend="strikethrough">ere</del> the shock <del rend="strikethrough">cease</del> to tingle</line>
    <line>One falls and then another in the <del rend="strikethrough">dust</del> path</line>
    <line><del rend="strikethrough">And</del> <del rend="strikethrough">The icy</del></line>
    <line><del rend="strikethrough">And over them</del></line>
    <line><del rend="strikethrough">And rain after</del></line>
    <line>And the cold desolation is <del rend="strikethrough">not single</del></line>
    <line>Senseless</line>
    <line><del rend="strikethrough">And</del> Nor is the desolation   single</line>
    <line><del rend="strikethrough">And</del> <del rend="strikethrough">And  over  them  the  light</del></line>
    <line>can</line>
    <line>Yet ere <del rend="strikethrough">I</del> <del rend="strikethrough">could</del> say where the chariot hath</line>
    <line>I find</line>
    <line>Past over them; nor other<del rend="strikethrough">s</del> trace <del rend="strikethrough">of</del> <del rend="strikethrough">remained</del></line>
    <line>foam   <del rend="strikethrough">when</del> <del rend="strikethrough">as</del>   <del rend="strikethrough">torrents</del></line>
    <line><unclear>Oceans</unclear> wrath</line>
    <line>But as of <del rend="strikethrough">smoke</del> upon the <del rend="strikethrough">stream</del>.</line>
    <line>after the Oceans</line>
    <line><del rend="strikethrough">rain<unclear>bows</unclear></del>        roar waves</line>
    <line><del rend="strikethrough">?Sun &amp; ,</del></line>
    <line>behind.</line>
    <line>Is spent upon the desert shore. &#8212; <del rend="strikethrough">The</del></line>
    <line>R</line>
    <line>The earthquake is rocking</line>
    <line>The corpse in its cradle within the grave</line>
    <line>The thunder is mocking</line>
    <line>The <del rend="strikethrough">yell</del> of the earth from its cloudy cave</line>
    <line>spasm</line>
    <line><del rend="strikethrough">The</del> The clear air awakes</line>
    <line>Ricetti</line>
    <line>Ricetti</line>
    <line>Ricetti Ricetti</line>
  </zone>
</surface>
