<?xml version="1.0" encoding="UTF-8"?>
<?xml-model href="../../../schemata/shelley-godwin-page.rng" type="application/xml" schematypens="http://purl.oclc.org/dsdl/schematron"?>
<?xml-model href="../../../schemata/shelley-godwin-page.rng" type="application/xml" schematypens="http://relaxng.org/ns/structure/1.0"?>
<surface xmlns="http://www.tei-c.org/ns/1.0" xmlns:mith="http://mith.umd.edu/sc/ns1#" ulx="0"
  uly="0" lrx="5406" lry="7052" xml:id="ox-ms_shelley_e3-0055" partOf="#ox-ms_shelley_e3" mith:folio="27r" mith:shelfmark="MS. Shelley e. 1">
  <graphic url="http://shelleygodwinarchive.org/images/ox/ox-ms_shelley_e3-0055.jp2"/>
  <zone type="library"><line rend="right">25</line></zone>
  <zone type="main">
    <milestone unit="tei:seg" spanTo="#e3-0055.01" corresp="e3-0054.04"/>
    <line>hues in their repose</line>
    <anchor xml:id="e3-0055.01"/>
    <line><add><metamark function="count">250</metamark></add></line>
  </zone>
</surface>
