<?xml version="1.0" encoding="ISO-8859-1"?><?xml-model href="../../../schemata/shelley-godwin-page.rnc"
  type="application/relax-ng-compact-syntax"?><?xml-stylesheet type="text/xsl"
  href="../../../xsl/page-proof.xsl"?>
<surface xmlns="http://www.tei-c.org/ns/1.0" xmlns:mith="http://mith.umd.edu/sc/ns1#"
  ulx="0" uly="0" lrx="5408" lry="7098"
  xml:id="ox-ms_shelley_adds_e11-0076" partOf="#ox-ms_shelley_adds_e11"
  mith:shelfmark="MS. Shelley adds. e. 11" mith:folio="74">
  <graphic url="http://shelleygodwinarchive.org/images/ox/ms_shelley_adds_e11/ms_shelley_adds_e11-0076.jp2"/>
  <zone type="main">
    <line>all</line>
    <line>And <del rend="strikethrough">all that</del> vain men</line>
    <line><del rend="strikethrough"><unclear>We</unclear> des</del> <del rend="strikethrough">And hope, &amp;</del></line>
    <line><del rend="strikethrough"><unclear>All</unclear> <unclear></unclear> things:</del></line>
    <line>And all that men imagine or believe</line>
    <line><unclear>pant</unclear>                may</line>
    <line><del rend="strikethrough">Of</del> Or hope can <del rend="strikethrough">form</del>, or suffering <del rend="strikethrough">can</del> atchieve</line>
    <line>for ever</line>
    <line>We descanted; &amp; I, <del rend="strikethrough">forever</del> still</line>
    <line>Is it not wise to make the best of ill?</line>
    <line>Argued against despondency, <unclear>B</unclear>ut pride</line>
    <line>Made my companion take the darker side</line>
    <line>The sense that he was greater than his</line>
    <line><unclear>his</unclear></line>
    <line>Had made made methinks <del rend="strikethrough">that</del> <del rend="strikethrough">ea</del></line>
    <line>By gazing on its own exceeding light</line>
    <line><del rend="strikethrough">the <unclear>sun</unclear></del></line>
    <line><del rend="strikethrough"><unclear>The</unclear> <unclear></unclear> <unclear></unclear> <unclear>of</unclear> <unclear>the</unclear> <unclear>horizon</unclear></del> of the</line>
    <line><unclear>Over</unclear> <del rend="strikethrough"><unclear>Sunk</unclear> <unclear>down</unclear> <unclear>among</unclear></del> <del rend="strikethrough">the</del> <del rend="strikethrough"><unclear>western</unclear></del> mountains - oh</line>
    <line><del rend="strikethrough"><unclear>How</unclear></del></line>
    <line>How beautiful is sunset when the glow</line>
    <line>Of Heaven descends upon a land like thee</line>
    <line>Thou Paradise of exiles, Italy !</line>
    <line><del rend="strikethrough">forests</del></line>
    <line><del rend="strikethrough">Upon the</del> <del rend="strikethrough">Oceans Vineyards</del>             <del rend="strikethrough">sea<unclear>s</unclear></del></line>
    <line><del rend="strikethrough">mountains</del>, <del rend="strikethrough">vineyards, rocks</del> <del rend="strikethrough">&amp; Oceans</del></line>
    <line><del rend="strikethrough">seas &amp; mountains</del></line>
    <line><del rend="strikethrough">Upon thin Oceans, and the mighty <unclear>domes</unclear></del> <del rend="strikethrough"><unclear>domes</unclear></del></line>
    <line><del rend="strikethrough">towers</del></line>
    <line><del rend="strikethrough">Of cities they encircle,</del> <del rend="strikethrough">&amp; the bowers</del></line>
  </zone>
</surface>
