<?xml version="1.0" encoding="ISO-8859-1"?><?xml-model href="../../../derivatives/shelley-godwin-page.rnc"
  type="application/relax-ng-compact-syntax"?><?xml-stylesheet type="text/xsl"
  href="../../../xsl/page-proof.xsl"?>
<surface xmlns="http://www.tei-c.org/ns/1.0" xmlns:sga="http://shelleygodwinarchive.org/ns/1.0" ulx="0" uly="0"
  lrx="5410" lry="7272" xml:id="ox-ms_shelley_e2-0007" partOf="#ox-ms_shelley_e2">
  <graphic url="http://shelleygodwinarchive.org/images/ox/ox-ms_shelley_e2-0007.jp2"/>
  <zone type="main">
    <line>3</line>
    <line>Ione</line>
    <line>Sister I hear the thunder of new wings</line>
    <line>Panthea</line>
    <line>These solid quiver</line>
    <line><del rend="strikethrough">Alas the</del> mountains <del rend="strikethrough">tremble</del> with the sound</line>
    <line>Even as the tremulous air &#8212; <del rend="strikethrough"><unclear>L</unclear>ook not I pray</del></line>
    <line>Thier shadows make</line>
    <line>The space within my plumes more black than night.</line>
  </zone>
</surface>

