<?xml version="1.0" encoding="UTF-8"?>
<?xml-model href="../../../schemata/shelley-godwin-page.rng" type="application/xml" schematypens="http://purl.oclc.org/dsdl/schematron"?>
<?xml-model href="../../../schemata/shelley-godwin-page.rng" type="application/xml" schematypens="http://relaxng.org/ns/structure/1.0"?>
<surface xmlns="http://www.tei-c.org/ns/1.0" xmlns:mith="http://mith.umd.edu/sc/ns1#"
  xml:id="ox-ms_abinger_c56-0024" ulx="0" uly="0" lrx="5364" lry="7104"
  mith:shelfmark="MS. Abinger c. 56" mith:folio="10v" partOf="#ox-frankenstein_volume_i">
  <graphic url="http://shelleygodwinarchive.org/images/ox/ms_abinger_c56/ms_abinger_c56-0024.jp2"/>
  <zone type="pagination" rend="bordered"><line>55</line></zone>
  
  <zone type="main">
    <line rend="center"><milestone unit="tei:head" spanTo="#c56-0024.04"/>Chap. 4<anchor xml:id="c56-0024.04"/></line>
    <line>The next morning I delivered my</line>
    <line>letters of introduction and paid a</line>
    <line>visit to some of the principal</line>
    <line>professors. and among others to M. <mod>
        <del rend="strikethrough">K</del>
        <del rend="unmarked">&#x2014;</del>
        <anchor xml:id="c56-0024.01"/>
      </mod></line>
    <line>Professor of <del rend="strikethrough">&#x26; Lecturer</del>
      <del rend="strikethrough">upon</del> Natural</line>
    <line>philosophy. He received me with</line>
    <line>politeness, and asked me several</line>
    <line>questions concerning my progress</line>
    <line>in the <del rend="strikethrough">sciences</del> different branches</line>
    <line>of science appertaining to natural</line>
    <line>philosophy. I mentioned, it is true</line>
    <line>with fear and trembling, the only</line>
    <line>authors I had <mod>
        <add place="sublinear"><metamark function="insert">^</metamark></add>
        <add place="superlinear">ever</add>
      </mod> read upon those</line>
    <line>subjects. The professor stared. <delSpan spanTo="#c56-0024.02" rend="strikethrough"/>I
      said</line>
    <line>that I did not mention these<anchor xml:id="c56-0024.02"/></line>
    <line>"Have you really" said<del rend="smear">"</del> he "spent</line>
    <line>"your time in studying such</line>
    <line>"nonsence?" I replied in the affir</line>
    <line>mative.</line>
    <milestone unit="tei:p"/>
    <line rend="indent1">"Every minute"&#x2013; continued M. <mod>
        <del rend="strikethrough">K</del>
        <del rend="unmarked">&#x2014;</del>
        <anchor xml:id="c56-0024.03"/>
      </mod></line>
    <line>with warmth," every instant that</line>
    <line>"you have wasted upon those</line>
    <line>"books is utterly and entirely lost.</line>
    <line>"You have burdened your <del rend="strikethrough">bur</del></line>
    <line>"<del rend="strikethrough">memor</del> memory with exploded</line>
    <line>"systems and useless names. Good</line>
    <line>"God <mod>
        <del rend="strikethrough">where must you</del>
        <add place="superlinear">in what desart land</add>
      </mod> have you</line>
    <line>"lived where no one was kind</line>
    <line>"enough to <del rend="strikethrough">enfor</del> inform you</line>
    <line>"that these fancies which <mod>
        <add place="sublinear"><metamark function="insert">^</metamark></add>
        <add place="superlinear">you</add>
      </mod> have</line>
  </zone>
  <zone type="left_margin" corresp="#c56-0024.01">
    <line><add><mod>
          <del rend="strikethrough">Krempe</del>
          <add place="sublinear">Krempe</add>
        </mod></add></line>
  </zone>
  <zone type="left_margin" corresp="#c56-0024.03">
    <line><add>Krempe</add></line>
  </zone>
</surface>
