<?xml version="1.0" encoding="UTF-8"?>
<?xml-model href="../../../schemata/shelley-godwin-page.rng" type="application/xml" schematypens="http://purl.oclc.org/dsdl/schematron"?>
<?xml-model href="../../../schemata/shelley-godwin-page.rng" type="application/xml" schematypens="http://relaxng.org/ns/structure/1.0"?>
<surface xmlns="http://www.tei-c.org/ns/1.0" xmlns:mith="http://mith.umd.edu/sc/ns1#"
  ulx="0" uly="0" lrx="5242" lry="6886"
  xml:id="ox-ms_shelley_adds_e12-0066" partOf="#ox-ms_shelley_adds_e12"
  mith:shelfmark="MS. Shelley adds. e. 12" mith:folio="64">
  <graphic url="http://shelleygodwinarchive.org/images/ox/ms_shelley_adds_e12/ms_shelley_adds_e12-0066.jp2"/>
  <zone type="main">
    <line>stream</line>
    <line>whose <del rend="strikethrough">path</del>, mid 2</line>
    <line>Thou, <del rend="strikethrough">up</del>on <del rend="strikethrough">whom in</del> the steep sky's commotion</line>
    <line>Loose clouds, like Earths decaying leaves,</line>
    <line>are shed</line>
    <line>Shook from the tangled boughs of Heaven</line>
    <line>&amp; Ocean</line>
    <line>thunder          is</line>
    <line>Angels of rain &amp; lightning &#8212; there <del rend="strikethrough">are</del> spread</line>
    <line>On the blue surface of thine aery surge,</line>
    <line>bright hair</line>
    <line>Like the <del rend="strikethrough">loose</del> <del rend="strikethrough">locks</del> uplifted from the head</line>
    <line>Of some fierce Maenad, even from the dim</line>
    <line>verge</line>
    <line>Of the horizon to the Zenith's height,</line>
    <line><del rend="strikethrough">locks</del></line>
    <line>The <del rend="strikethrough">hair</del> of the approaching storm. Thou</line>
    <line>Dirge</line>
    <line><del rend="strikethrough"><unclear>For</unclear></del> Of the dying year, to which this closing</line>
    <line>night . . .</line>
    <line>Will be the dome of a vast sepulchre</line>
    <line>Vaulted with all thy congregated might</line>
    <line>whose solid atmosphere</line>
    <line>Of vapours, from <del rend="strikethrough">which lightning</del></line>
    <line>Black <del rend="strikethrough">floods</del> &amp; fire &amp; hail will     o hear</line>
    <line>rain                    burst &#8212;</line>
  </zone>
</surface>
